ExcellentLibrary/ExcellentLibrary.py
ExcellentLibrary/__init__.py
robotframework_excellentlibrary-1.0.0.dist-info/METADATA
robotframework_excellentlibrary-1.0.0.dist-info/WHEEL
robotframework_excellentlibrary-1.0.0.dist-info/top_level.txt
robotframework_excellentlibrary-1.0.0.dist-info/RECORD
