Metadata-Version: 2.1
Name: robotframework-excellentlibrary
Version: 1.0.0
Summary: A really useful Robot Framework library for working with Excel 2010 (and above) files.
Home-page: https://github.com/bartkl/robotframework-excellentlibrary
Author: Bart Kleijngeld
Author-email: bartkl@gmail.com
License: UNKNOWN
Keywords: excel testing robotframework robotframework-excellibrary robotframework-excellib
Platform: UNKNOWN
Classifier: Programming Language :: Python :: 3
Classifier: Operating System :: OS Independent
Requires-Python: ~=3.6
Requires-Dist: openpyxl (>=3.0.3)
